hw_files/dlatch.v
module dlatch(d, clk, q);
    input d, clk;
    output q;
    reg q;
    always @(clk,d) begin
        casex({clk,d})
        2'b1x: q = d; endcase
    end
endmodule

hw_files/dff.v
module dff(d, clk, q);
    input d, clk;
    output q;
    reg q;
    always @(posedge clk) begin
        casex({clk,d})
        2'b1x: q = d; endcase
    end
endmodule

hw_files/d_tb.v
`include "dff.v"
`include "dlatch.v"
module d_tb; 
    reg d, clk;
    wire ql, qff;
    dff DFF(d,clk,qff);
    dlatch DL(d,clk,ql);

    initial begin 
        d = 0; 
        clk = 0; 

        #80 
        $finish;
    end 

    always 
        #15 d = ~d;
    always 
        #10 clk = ~clk;

    always @(d, clk, ql, qff) begin 
        #1
        $display("d: %b, clk: %b ==> dff: %b, dl: %b", d, clk, qff, ql);
    end 

    initial begin 
        $dumpfile("d_tb.vcd");
        $dumpvars(0, d_tb);
    end
endmodule

hw_files/d_tb.vcd
$date
	Fri Sep 23 15:15:54 2022
$end
$version
	Icarus Verilog
$end
$timescale
	1s
$end
$scope module d_tb $end
$var wire 1 ! ql $end
$var wire 1 " qff $end
$var reg 1 # clk $end
$var reg 1 $ d $end
$scope module DFF $end
$var wire 1 # clk $end
$var wire 1 $ d $end
$var reg 1 " q $end
$upscope $end
$scope module DL $end
$var wire 1 # clk $end
$var wire 1 $ d $end
$var reg 1 ! q $end
$upscope $end
$upscope $end
$enddefinitions $end
#0
$dumpvars
0$
0#
x"
x!
$end
#10
0"
0!
1#
#15
1!
1$
#20
0#
#30
0!
1#
0$
#40
0#
#45
1$
#50
1"
1!
1#
#60
0#
0$
#70
0"
0!
1#
#75
1!
1$
