Lab2/full_adder_nand.v
module full_adder_nand(S, Cout, A, B, Cin);
    input A, B, Cin;
    output S, Cout; 
    wire w1, w2, w3, w4, w5, w6, w7;
    nand N1(w1, A, B);
    nand N2(w2, A, w1);
    nand N3(w3, B, w1);
    nand N4(w4, w2, w3); 
    nand N5(w5, w4, Cin); 
    nand N6(w6, w5, w4); 
    nand N7(w7, Cin, w5); 
    nand N8(S, w6, w7); 
    nand N9(Cout, w5, w1);
endmodule

Lab2/full_adder_nand_tb.v
`timescale 1ns/100ps


module full_adder_nand_tb;
    reg A, B, Cin; 
    wire S, Cout; 

    full_adder_nand adder(.A(A), .B(B), .Cin(Cin), .S(S), .Cout(Cout));

    initial begin 
        A =0;
        B =0;
    Cin =0; 
    #80 
    $finish;
    end

    always 
        #10 A = ~A;
    always
        #20 B = ~B;
    always
        #40 Cin = ~Cin;

    always @(A, B, Cin) begin 
        #1 
        $display("A:%b, B:%b, Cin:%b => S:%b, Cout:%b", A, B, Cin, S, Cout);
    end 

    initial begin 
        $dumpfile("full_adder.vcd");
        $dumpvars(0, full_adder_nand_tb);
    end 
endmodule

Lab2/full_adder.vcd
$date
	Tue Sep  6 15:25:49 2022
$end
$version
	Icarus Verilog
$end
$timescale
	100ps
$end
$scope module full_adder_nand_tb $end
$var wire 1 ! S $end
$var wire 1 " Cout $end
$var reg 1 # A $end
$var reg 1 $ B $end
$var reg 1 % Cin $end
$scope module adder $end
$var wire 1 # A $end
$var wire 1 $ B $end
$var wire 1 % Cin $end
$var wire 1 " Cout $end
$var wire 1 ! S $end
$var wire 1 & w1 $end
$var wire 1 ' w2 $end
$var wire 1 ( w3 $end
$var wire 1 ) w4 $end
$var wire 1 * w5 $end
$var wire 1 + w6 $end
$var wire 1 , w7 $end
$upscope $end
$upscope $end
$enddefinitions $end
#0
$dumpvars
1,
1+
1*
0)
1(
1'
1&
0%
0$
0#
0"
0!
$end
#100
1!
0+
1)
0'
1#
#200
1'
0(
0#
1$
#300
0!
1+
0)
1(
1"
0&
1'
1#
#400
0"
1!
1&
0,
0#
0$
1%
#500
0!
1,
1"
0*
1+
1)
0'
1#
#600
1'
0(
0#
1$
#700
1!
0,
1*
0)
1(
0&
1'
1#
#800
0"
0!
1&
1,
0#
0$
0%
